hypixel/__init__.py
hypixel/errors.py
hypixel/hypixel.py
MinecraftaPY-0.0.2.dist-info/LICENSE
MinecraftaPY-0.0.2.dist-info/METADATA
MinecraftaPY-0.0.2.dist-info/WHEEL
MinecraftaPY-0.0.2.dist-info/top_level.txt
MinecraftaPY-0.0.2.dist-info/RECORD
