Metadata-Version: 2.1
Name: MinecraftaPY
Version: 0.0.2
Summary: Simple wrapper for Hypixel and Mojang's APIs. WIP, very unstable!
Home-page: https://github.com/ThisIsanAlt/MinecraftaPY
Author: ThisIsanAlt
License: UNKNOWN
Project-URL: Bug Tracker, https://github.com/ThisIsanAlt/MinecraftaPY/issues
Platform: UNKNOWN
Classifier: Programming Language :: Python :: 3
Classifier: License :: OSI Approved :: MIT License
Classifier: Operating System :: OS Independent
Requires-Python: >=3.6
License-File: LICENSE
